moe/__init__.py
moe/add/__init__.py
moe/add/add_cli.py
moe/add/add_core.py
moe/cli.py
moe/config.py
moe/duplicate/__init__.py
moe/duplicate/dup_cli.py
moe/duplicate/dup_core.py
moe/edit/__init__.py
moe/edit/edit_cli.py
moe/edit/edit_core.py
moe/library/__init__.py
moe/library/album.py
moe/library/extra.py
moe/library/lib_item.py
moe/library/track.py
moe/list.py
moe/moe_alembic/README
moe/moe_alembic/alembic.ini
moe/moe_alembic/env.py
moe/moe_alembic/script.py.mako
moe/moe_alembic/versions/0ce5960a081e_new_field_catalog_nums.py
moe/moe_alembic/versions/16590851e88e_new_field_composer_sort.py
moe/moe_alembic/versions/30668259fcd6_new_field_country.py
moe/moe_alembic/versions/31e896e9a709_new_field_composer.py
moe/moe_alembic/versions/32e9fea590b7_new_field_track_total.py
moe/moe_alembic/versions/60608d9d2908_new_field_media.py
moe/moe_alembic/versions/6d4e785df5cb_initial_generation.py
moe/moe_alembic/versions/817440447857_new_field_label.py
moe/moe_alembic/versions/880c5a2d80ed_remove_audio_format_field.py
moe/moe_alembic/versions/ab11c34c1d0b_new_field_audio_format.py
moe/moe_alembic/versions/ab5db9861d30_rename_custom_fields.py
moe/moe_alembic/versions/bf49ac6805f7_json_multi_value_fields.py
moe/moe_alembic/versions/db3a470892c6_new_field_og_date.py
moe/moe_alembic/versions/eb8c7e20a080_new_field_barcode.py
moe/moe_alembic/versions/fe0956c93730_new_field_artists.py
moe/moe_import/__init__.py
moe/moe_import/import_cli.py
moe/moe_import/import_core.py
moe/move/__init__.py
moe/move/move_cli.py
moe/move/move_core.py
moe/py.typed
moe/query.py
moe/read/__init__.py
moe/read/read_cli.py
moe/read/read_core.py
moe/remove/__init__.py
moe/remove/rm_cli.py
moe/remove/rm_core.py
moe/util/__init__.py
moe/util/cli/__init__.py
moe/util/cli/prompt.py
moe/util/cli/query.py
moe/util/core/__init__.py
moe/util/core/match.py
moe/write.py
moe-2.5.0.dist-info/LICENSE
moe-2.5.0.dist-info/METADATA
moe-2.5.0.dist-info/WHEEL
moe-2.5.0.dist-info/entry_points.txt
moe-2.5.0.dist-info/RECORD
