Metadata-Version: 2.3
Name: Moe
Version: 2.5.0
Summary: The ultimate tool for managing your music library.
License: MIT
Author: Jacob Pavlock
Author-email: jtpavlock@gmail.com
Requires-Python: >=3.9,<3.14
Classifier: Development Status :: 5 - Production/Stable
Classifier: License :: OSI Approved :: MIT License
Classifier: Programming Language :: Python :: 3
Classifier: Programming Language :: Python :: 3.9
Classifier: Programming Language :: Python :: 3.10
Classifier: Programming Language :: Python :: 3.11
Classifier: Programming Language :: Python :: 3.12
Classifier: Programming Language :: Python :: 3.13
Classifier: Topic :: Multimedia :: Sound/Audio :: Editors
Requires-Dist: SQLAlchemy (>=2.0.0,<3.0.0)
Requires-Dist: Unidecode (>=1.2.0,<2.0.0)
Requires-Dist: alembic (>=1.4.2,<2.0.0)
Requires-Dist: dynaconf (>=3.1.4,<4.0.0)
Requires-Dist: importlib-metadata (>=7.0.1,<8.0.0)
Requires-Dist: mediafile (>=0.13.0,<0.14.0)
Requires-Dist: musicbrainzngs (>=0.7.1,<0.8.0)
Requires-Dist: pluggy (>=1.3.0,<2.0.0)
Requires-Dist: questionary (>=2.0.0,<3.0.0)
Requires-Dist: rich (>=13.0.0,<14.0.0)
Project-URL: Documentation, https://mrmoe.readthedocs.io/en/latest/index.html
Project-URL: Repository, https://github.com/MoeMusic/Moe
